cunyfirstapi/__init__.py
cunyfirstapi/actions_locations.py
cunyfirstapi/class_search.py
cunyfirstapi/constants.py
cunyfirstapi/cunyfirstapi.py
cunyfirstapi/enroll.py
cunyfirstapi/grades.py
cunyfirstapi/helper.py
cunyfirstapi/locations_enum.py
cunyfirstapi/login.py
cunyfirstapi/redacted_stdout.py
cunyfirstapi/student_center.py
cunyfirstapi/transcript.py
tests/__init__.py
tests/redacted_stdout.py
tests/run_tests.py
cunyfirstapi-0.0.18.dist-info/LICENSE
cunyfirstapi-0.0.18.dist-info/METADATA
cunyfirstapi-0.0.18.dist-info/WHEEL
cunyfirstapi-0.0.18.dist-info/top_level.txt
cunyfirstapi-0.0.18.dist-info/RECORD
