Metadata-Version: 2.1
Name: cunyfirstapi
Version: 0.0.18
Summary: A simple CUNYFIRST python API
Home-page: https://github.com/CUNYSuite/CunyFirstAPI
Author: Ehud Adler
Author-email: ehud.adler62@qmail.cuny.edu
License: UNKNOWN
Platform: UNKNOWN
Classifier: Programming Language :: Python :: 3
Classifier: License :: OSI Approved :: MIT License
Classifier: Operating System :: OS Independent
